LICENSE
MANIFEST.in
Makefile
setup.cfg
setup.py
Flask_RESTbolt.egg-info/PKG-INFO
Flask_RESTbolt.egg-info/SOURCES.txt
Flask_RESTbolt.egg-info/dependency_links.txt
Flask_RESTbolt.egg-info/not-zip-safe
Flask_RESTbolt.egg-info/requires.txt
Flask_RESTbolt.egg-info/top_level.txt
docs/Makefile
docs/api.rst
docs/conf.py
docs/contents.rst.inc
docs/extending.rst
docs/fields.rst
docs/index.rst
docs/installation.rst
docs/intermediate-usage.rst
docs/make.bat
docs/quickstart.rst
docs/testing.rst
docs/_static/flask-restful-small.png
docs/_static/flask-restful.png
docs/_templates/sidebarintro.html
docs/_templates/sidebarlogo.html
examples/todo.py
examples/todo_simple.py
examples/xml_representation.py
flask_restbolt/__init__.py
flask_restbolt/__version__.py
flask_restbolt/api.py
flask_restbolt/fields.py
flask_restbolt/inputs.py
flask_restbolt/paging.py
flask_restbolt/permissions.py
flask_restbolt/resources.py
flask_restbolt/serializers.py
flask_restbolt/representations/__init__.py
flask_restbolt/representations/json.py
flask_restbolt/utils/__init__.py
flask_restbolt/utils/cors.py
flask_restbolt/utils/crypto.py
tests/README.md
tests/__init__.py
tests/requirements.txt
tests/test_accept.py
tests/test_api.py
tests/test_api_with_blueprint.py
tests/test_cors.py
tests/test_crypto.py
tests/test_fields.py
tests/test_inputs.py
tests/test_paging.py
tests/.git/COMMIT_EDITMSG
tests/.git/HEAD
tests/.git/config
tests/.git/description
tests/.git/index
tests/.git/hooks/applypatch-msg.sample
tests/.git/hooks/commit-msg.sample
tests/.git/hooks/post-update.sample
tests/.git/hooks/pre-applypatch.sample
tests/.git/hooks/pre-commit.sample
tests/.git/hooks/pre-push.sample
tests/.git/hooks/pre-rebase.sample
tests/.git/hooks/prepare-commit-msg.sample
tests/.git/hooks/update.sample
tests/.git/info/exclude
tests/.git/objects/03/64a5fbd99bcc92a39a7b1d94640ca46d6b0872
tests/.git/objects/3c/5df12d301cec980480a109d66763343ede1ac3
tests/.git/objects/4f/6e61382a1f4a860d308a1b3565fcd9b22635e9
tests/.git/objects/50/e0f72fb4c631cd528986cc3b0c25aade0ddc02
tests/.git/objects/59/04fbe843f83dfa15ce40ea8b583be0b2afbef6
tests/.git/objects/60/aca18b808a074b17609696c0388f46a66136f8
tests/.git/objects/9e/5efb38f2f2a37a7185e708f8ad254b9ec634c1
