Metadata-Version: 1.1
Name: Flask-RESTbolt
Version: 0.1.0
Summary: Powerful and fast framework for creating REST APIs with Flask
Home-page: https://github.com/costular/flask-restbolt/
Author: Costular
Author-email: costular@gmail.com
License: BSD
Keywords: flask rest,flask restful,restbolt,flask restbolt,flask api,flask api rest
Platform: any
Classifier: Framework :: Flask
Classifier: Programming Language :: Python :: 2
Classifier: Programming Language :: Python :: 2.6
Classifier: Programming Language :: Python :: 2.7
Classifier: Programming Language :: Python :: 3
Classifier: Programming Language :: Python :: 3.3
Classifier: Programming Language :: Python :: 3.4
Classifier: Programming Language :: Python :: 3.5
Classifier: Programming Language :: Python :: 3.6
Classifier: License :: OSI Approved :: BSD License
